{
  "config": {
    "step": {
      "user": {
        "title": "Select HomeKit Bridges",
        "description": "Select one or more HomeKit Bridges to manage. Found {bridge_count} available bridge(s).",
        "data": {
          "managed_bridges": "HomeKit Bridges"
        }
      },
      "bridge": {
        "title": "Configure {bridge_name}",
        "description": "Step {current_index} of {bridge_total}. Choose the allowed Home Assistant Areas, optional default room label, and provide optional include/exclude entity overrides (comma or newline separated entity IDs). Include overrides always win over area filters.",
        "data": {
          "allowed_areas": "Allowed Areas",
          "default_room": "Default HomeKit Room (optional)",
          "include_entities": "Include entity overrides",
          "exclude_entities": "Exclude entity overrides"
        }
      }
    },
    "abort": {
      "no_bridges": "No HomeKit Bridge configurations found. Please set up the HomeKit Bridge integration first.",
      "all_bridges_configured": "All available HomeKit Bridges have already been configured."
    },
    "error": {
      "invalid_bridge": "The selected bridge is not valid or no longer exists.",
      "select_bridge": "Select at least one bridge to continue."
    }
  },
  "options": {
    "step": {
      "init": {
        "title": "Select Bridges to Manage",
        "description": "Update which HomeKit Bridges this entry manages. Existing bridge-specific filters will be requested next.",
        "data": {
          "managed_bridges": "HomeKit Bridges"
        }
      },
      "bridge": {
        "title": "Update {bridge_name}",
        "description": "Step {current_index} of {bridge_total}. Adjust allowed areas, default room and include/exclude overrides.",
        "data": {
          "allowed_areas": "Allowed Areas",
          "default_room": "Default HomeKit Room (optional)",
          "include_entities": "Include entity overrides",
          "exclude_entities": "Exclude entity overrides"
        }
      }
    }
  }
}

